{
  "9745a24d531e": {
    "path": "/schemaExtensions",
    "ps_commands": [
      {
        "name": "Get-MgSchemaExtension",
        "method": "GET",
        "apiReference": "https://learn.microsoft.com/graph/api/schemaextension-list?v",
        "permissions": [
          "User.Read",
          "Application.Read.All"
        ]
      },
      {
        "name": "New-MgSchemaExtension",
        "method": "POST",
        "apiReference": "https://learn.microsoft.com/graph/api/schemaextension-post-s",
        "permissions": [
          "Application.ReadWrite.All",
          "Directory.ReadWrite.All"
        ]
      }
    ],
    "permissions": [
      "Application.Read.All",
      "Application.ReadWrite.All",
      "Directory.ReadWrite.All",
      "User.Read"
    ],
    "apiReferences": [
      "https://learn.microsoft.com/graph/api/schemaextension-list?v",
      "https://learn.microsoft.com/graph/api/schemaextension-post-s"
    ]
  },
  "a5e93390e7fd": {
    "path": "/schemaExtensions/{schemaExtension-id}",
    "ps_commands": [
      {
        "name": "Get-MgSchemaExtension",
        "method": "GET",
        "apiReference": "https://learn.microsoft.com/graph/api/schemaextension-get?vi",
        "permissions": [
          "User.Read",
          "Application.Read.All"
        ]
      },
      {
        "name": "Remove-MgSchemaExtension",
        "method": "DELETE",
        "apiReference": "https://learn.microsoft.com/graph/api/schemaextension-delete",
        "permissions": [
          "Application.ReadWrite.All",
          "Directory.ReadWrite.All"
        ]
      },
      {
        "name": "Update-MgSchemaExtension",
        "method": "PATCH",
        "apiReference": "https://learn.microsoft.com/graph/api/schemaextension-update",
        "permissions": [
          "Application.ReadWrite.All",
          "Directory.ReadWrite.All"
        ]
      }
    ],
    "permissions": [
      "Application.Read.All",
      "Application.ReadWrite.All",
      "Directory.ReadWrite.All",
      "User.Read"
    ],
    "apiReferences": [
      "https://learn.microsoft.com/graph/api/schemaextension-delete",
      "https://learn.microsoft.com/graph/api/schemaextension-get?vi",
      "https://learn.microsoft.com/graph/api/schemaextension-update"
    ]
  },
  "5f208614069b": {
    "path": "/schemaExtensions/$count",
    "ps_commands": [
      {
        "name": "Get-MgSchemaExtension",
        "method": "GET",
        "apiReference": "https://learn.microsoft.com/graph/api/schemaextension-list?v",
        "permissions": [
          "User.Read",
          "Application.Read.All"
        ]
      },
      {
        "name": "New-MgSchemaExtension",
        "method": "POST",
        "apiReference": "https://learn.microsoft.com/graph/api/schemaextension-post-s",
        "permissions": [
          "Application.ReadWrite.All",
          "Directory.ReadWrite.All"
        ]
      }
    ],
    "permissions": [
      "Application.Read.All",
      "Application.ReadWrite.All",
      "Directory.ReadWrite.All",
      "User.Read"
    ],
    "apiReferences": [
      "https://learn.microsoft.com/graph/api/schemaextension-list?v",
      "https://learn.microsoft.com/graph/api/schemaextension-post-s"
    ]
  }
}