{
  "/print/printers/{printer-id}/jobs/{printJob-id}/documents/$count": {
    "get": {
      "tags": [
        "print.printer"
      ],
      "summary": "Get the number of the resource",
      "operationId": "print.printer.job.document_GetCount",
      "parameters": [
        {
          "name": "printer-id",
          "in": "path",
          "description": "The unique identifier of printer",
          "required": true,
          "style": "simple",
          "schema": {
            "type": "string"
          },
          "x-ms-docs-key-type": "printer"
        },
        {
          "name": "printJob-id",
          "in": "path",
          "description": "The unique identifier of printJob",
          "required": true,
          "style": "simple",
          "schema": {
            "type": "string"
          },
          "x-ms-docs-key-type": "printJob"
        },
        {
          "name": "$search",
          "in": "query",
          "description": "Search items by search phrases",
          "style": "form",
          "explode": false,
          "schema": {
            "type": "string"
          }
        },
        {
          "name": "$filter",
          "in": "query",
          "description": "Filter items by property values",
          "style": "form",
          "explode": false,
          "schema": {
            "type": "string"
          }
        }
      ],
      "responses": {
        "2XX": {
          "$ref": "#/components/responses/ODataCountResponse"
        },
        "default": {
          "$ref": "#/components/responses/error"
        }
      }
    }
  }
}