{
  "/print/shares/{printerShare-id}/jobs/{printJob-id}/microsoft.graph.abort": {
    "post": {
      "tags": [
        "print.Actions"
      ],
      "summary": "Invoke action abort",
      "description": "Abort a print job. Only applications using application permissions can abort a print job. Aborting a print job will only succeed if there is a printTask in a processing state on the associated print job, started by a trigger that the requesting app created. For details about how to register a task trigger, see Extending Universal Print to support pull printing.",
      "externalDocs": {
        "description": "Find more info here",
        "url": "https://learn.microsoft.com/graph/api/printjob-abort?view=graph-rest-beta"
      },
      "operationId": "print.share.job_abort",
      "parameters": [
        {
          "name": "printerShare-id",
          "in": "path",
          "description": "The unique identifier of printerShare",
          "required": true,
          "style": "simple",
          "schema": {
            "type": "string"
          },
          "x-ms-docs-key-type": "printerShare"
        },
        {
          "name": "printJob-id",
          "in": "path",
          "description": "The unique identifier of printJob",
          "required": true,
          "style": "simple",
          "schema": {
            "type": "string"
          },
          "x-ms-docs-key-type": "printJob"
        }
      ],
      "requestBody": {
        "description": "Action parameters",
        "content": {
          "application/json": {
            "schema": {
              "type": "object",
              "properties": {
                "reason": {
                  "type": "string",
                  "nullable": true
                }
              },
              "additionalProperties": {
                "type": "object"
              }
            }
          }
        },
        "required": true
      },
      "responses": {
        "2XX": {
          "description": "Success"
        },
        "default": {
          "$ref": "#/components/responses/error"
        }
      },
      "x-ms-docs-operation-type": "action"
    }
  }
}