{
  "/education/classes/{educationClass-id}/microsoft.graph.getRecentlyModifiedSubmissions()": {
    "get": {
      "tags": [
        "education.Functions"
      ],
      "summary": "Invoke function getRecentlyModifiedSubmissions",
      "description": "Retrieve submissions modified in the previous seven days. Only teachers and applications with application permissions can perform this operation. A submission object represents a student's work for an assignment. Resources associated with the submission represent their work. A teacher or application with application permissions has full access to all submission objects. The grade and feedback from a teacher are part of the educationOutcome associated with this object. Only teachers or applications with application permissions can add or change grades and feedback. Students can't see the grade or feedback until the assignment is released.",
      "externalDocs": {
        "description": "Find more info here",
        "url": "https://learn.microsoft.com/graph/api/educationclass-getrecentlymodifiedsubmissions?view=graph-rest-beta"
      },
      "operationId": "education.class_getRecentlyModifiedSubmission",
      "parameters": [
        {
          "name": "educationClass-id",
          "in": "path",
          "description": "The unique identifier of educationClass",
          "required": true,
          "style": "simple",
          "schema": {
            "type": "string"
          },
          "x-ms-docs-key-type": "educationClass"
        },
        {
          "name": "$top",
          "in": "query",
          "description": "Show only the first n items",
          "style": "form",
          "explode": false,
          "schema": {
            "minimum": 0,
            "type": "integer"
          },
          "example": 50
        },
        {
          "name": "$skip",
          "in": "query",
          "description": "Skip the first n items",
          "style": "form",
          "explode": false,
          "schema": {
            "minimum": 0,
            "type": "integer"
          }
        },
        {
          "name": "$search",
          "in": "query",
          "description": "Search items by search phrases",
          "style": "form",
          "explode": false,
          "schema": {
            "type": "string"
          }
        },
        {
          "name": "$filter",
          "in": "query",
          "description": "Filter items by property values",
          "style": "form",
          "explode": false,
          "schema": {
            "type": "string"
          }
        },
        {
          "name": "$count",
          "in": "query",
          "description": "Include count of items",
          "style": "form",
          "explode": false,
          "schema": {
            "type": "boolean"
          }
        },
        {
          "name": "$select",
          "in": "query",
          "description": "Select properties to be returned",
          "style": "form",
          "explode": false,
          "schema": {
            "uniqueItems": true,
            "type": "array",
            "items": {
              "type": "string"
            }
          }
        },
        {
          "name": "$orderby",
          "in": "query",
          "description": "Order items by property values",
          "style": "form",
          "explode": false,
          "schema": {
            "uniqueItems": true,
            "type": "array",
            "items": {
              "type": "string"
            }
          }
        },
        {
          "name": "$expand",
          "in": "query",
          "description": "Expand related entities",
          "style": "form",
          "explode": false,
          "schema": {
            "uniqueItems": true,
            "type": "array",
            "items": {
              "type": "string"
            }
          }
        }
      ],
      "responses": {
        "2XX": {
          "description": "Success",
          "content": {
            "application/json": {
              "schema": {
                "title": "Collection of educationSubmission",
                "type": "object",
                "properties": {
                  "value": {
                    "type": "array",
                    "items": {
                      "$ref": "#/components/schemas/microsoft.graph.educationSubmission"
                    }
                  },
                  "@odata.nextLink": {
                    "type": "string",
                    "nullable": true
                  }
                },
                "additionalProperties": {
                  "type": "object"
                }
              }
            }
          }
        },
        "default": {
          "$ref": "#/components/responses/error"
        }
      },
      "x-ms-docs-operation-type": "function",
      "x-ms-pageable": {
        "nextLinkName": "@odata.nextLink",
        "operationName": "listMore"
      }
    }
  }
}