{
  "/deviceManagement/remoteAssistancePartners/{remoteAssistancePartner-id}/microsoft.graph.beginOnboarding": {
    "post": {
      "tags": [
        "deviceManagement.Actions"
      ],
      "summary": "Invoke action beginOnboarding",
      "description": "A request to start onboarding.  Must be coupled with the appropriate TeamViewer account information",
      "operationId": "deviceManagement.remoteAssistancePartner_beginOnboarding",
      "parameters": [
        {
          "name": "remoteAssistancePartner-id",
          "in": "path",
          "description": "The unique identifier of remoteAssistancePartner",
          "required": true,
          "style": "simple",
          "schema": {
            "type": "string"
          },
          "x-ms-docs-key-type": "remoteAssistancePartner"
        }
      ],
      "responses": {
        "2XX": {
          "description": "Success"
        },
        "default": {
          "$ref": "#/components/responses/error"
        }
      },
      "x-ms-docs-operation-type": "action"
    }
  }
}