{
  "/organization/{organization-id}/branding": {
    "get": {
      "tags": [
        "organization.organizationalBranding"
      ],
      "summary": "Get organizationalBranding",
      "description": "Retrieve the default organizational branding object, if the Accept-Language header is set to 0 or default. If no default organizational branding object exists, this method returns a 404 Not Found error. If the Accept-Language header is set to an existing locale identified by the value of its id, this method retrieves the branding for the specified locale. This method retrieves only non-Stream properties, for example, usernameHintText and signInPageText. To retrieve Stream types of the default branding, for example, bannerLogo and backgroundImage, use the GET organizationalBrandingLocalization method.",
      "externalDocs": {
        "description": "Find more info here",
        "url": "https://learn.microsoft.com/graph/api/organizationalbranding-get?view=graph-rest-beta"
      },
      "operationId": "organization_GetBranding",
      "parameters": [
        {
          "name": "organization-id",
          "in": "path",
          "description": "The unique identifier of organization",
          "required": true,
          "style": "simple",
          "schema": {
            "type": "string"
          },
          "x-ms-docs-key-type": "organization"
        },
        {
          "name": "$select",
          "in": "query",
          "description": "Select properties to be returned",
          "style": "form",
          "explode": false,
          "schema": {
            "uniqueItems": true,
            "type": "array",
            "items": {
              "type": "string"
            }
          }
        },
        {
          "name": "$expand",
          "in": "query",
          "description": "Expand related entities",
          "style": "form",
          "explode": false,
          "schema": {
            "uniqueItems": true,
            "type": "array",
            "items": {
              "type": "string"
            }
          }
        }
      ],
      "responses": {
        "2XX": {
          "description": "Retrieved navigation property",
          "content": {
            "application/json": {
              "schema": {
                "$ref": "#/components/schemas/microsoft.graph.organizationalBranding"
              }
            }
          }
        },
        "default": {
          "$ref": "#/components/responses/error"
        }
      },
      "x-ms-docs-operation-type": "operation"
    },
    "patch": {
      "tags": [
        "organization.organizationalBranding"
      ],
      "summary": "Update organizationalBranding",
      "description": "Update the properties of the default branding object specified by the organizationalBranding resource.",
      "externalDocs": {
        "description": "Find more info here",
        "url": "https://learn.microsoft.com/graph/api/organizationalbranding-update?view=graph-rest-beta"
      },
      "operationId": "organization_UpdateBranding",
      "parameters": [
        {
          "name": "organization-id",
          "in": "path",
          "description": "The unique identifier of organization",
          "required": true,
          "style": "simple",
          "schema": {
            "type": "string"
          },
          "x-ms-docs-key-type": "organization"
        }
      ],
      "requestBody": {
        "description": "New navigation property values",
        "content": {
          "application/json": {
            "schema": {
              "$ref": "#/components/schemas/microsoft.graph.organizationalBranding"
            }
          }
        },
        "required": true
      },
      "responses": {
        "2XX": {
          "description": "Success",
          "content": {
            "application/json": {
              "schema": {
                "$ref": "#/components/schemas/microsoft.graph.organizationalBranding"
              }
            }
          }
        },
        "default": {
          "$ref": "#/components/responses/error"
        }
      },
      "x-ms-docs-operation-type": "operation"
    },
    "delete": {
      "tags": [
        "organization.organizationalBranding"
      ],
      "summary": "Delete organizationalBranding",
      "description": "Delete the default organizational branding object. To delete the organizationalBranding object, all images (Stream types) must first be removed from the object.",
      "externalDocs": {
        "description": "Find more info here",
        "url": "https://learn.microsoft.com/graph/api/organizationalbranding-delete?view=graph-rest-beta"
      },
      "operationId": "organization_DeleteBranding",
      "parameters": [
        {
          "name": "organization-id",
          "in": "path",
          "description": "The unique identifier of organization",
          "required": true,
          "style": "simple",
          "schema": {
            "type": "string"
          },
          "x-ms-docs-key-type": "organization"
        },
        {
          "name": "If-Match",
          "in": "header",
          "description": "ETag",
          "style": "simple",
          "schema": {
            "type": "string"
          }
        }
      ],
      "responses": {
        "2XX": {
          "description": "Success"
        },
        "default": {
          "$ref": "#/components/responses/error"
        }
      },
      "x-ms-docs-operation-type": "operation"
    }
  }
}