{
  "/users/{user-id}/ownedDevices/{directoryObject-id}": {
    "get": {
      "tags": [
        "users.directoryObject"
      ],
      "summary": "Get ownedDevices from users",
      "description": "Devices owned by the user. Read-only. Nullable. Supports $expand.",
      "operationId": "user_GetOwnedDevice",
      "parameters": [
        {
          "name": "user-id",
          "in": "path",
          "description": "The unique identifier of user",
          "required": true,
          "style": "simple",
          "schema": {
            "type": "string"
          },
          "x-ms-docs-key-type": "user"
        },
        {
          "name": "directoryObject-id",
          "in": "path",
          "description": "The unique identifier of directoryObject",
          "required": true,
          "style": "simple",
          "schema": {
            "type": "string"
          },
          "x-ms-docs-key-type": "directoryObject"
        },
        {
          "name": "ConsistencyLevel",
          "in": "header",
          "description": "Indicates the requested consistency level. Documentation URL: https://docs.microsoft.com/graph/aad-advanced-queries",
          "style": "simple",
          "schema": {
            "type": "string"
          },
          "examples": {
            "example-1": {
              "description": "$search and $count queries require the client to set the ConsistencyLevel HTTP header to 'eventual'.",
              "value": "eventual"
            }
          }
        },
        {
          "name": "$select",
          "in": "query",
          "description": "Select properties to be returned",
          "style": "form",
          "explode": false,
          "schema": {
            "uniqueItems": true,
            "type": "array",
            "items": {
              "type": "string"
            }
          }
        },
        {
          "name": "$expand",
          "in": "query",
          "description": "Expand related entities",
          "style": "form",
          "explode": false,
          "schema": {
            "uniqueItems": true,
            "type": "array",
            "items": {
              "type": "string"
            }
          }
        }
      ],
      "responses": {
        "2XX": {
          "description": "Retrieved navigation property",
          "content": {
            "application/json": {
              "schema": {
                "$ref": "#/components/schemas/microsoft.graph.directoryObject"
              }
            }
          }
        },
        "default": {
          "$ref": "#/components/responses/error"
        }
      },
      "deprecated": true,
      "x-ms-deprecation": {
        "removalDate": "2025-07-02",
        "date": "2024-07-02",
        "version": "2024-07/PrivatePreview:copilotExportAPI"
      },
      "x-ms-docs-operation-type": "operation"
    }
  }
}