{
  "/users/{user-id}/todo/lists/{todoTaskList-id}/tasks/{todoTask-id}/attachmentSessions/{attachmentSession-id}": {
    "get": {
      "tags": [
        "users.todo"
      ],
      "summary": "Get attachmentSessions from users",
      "operationId": "user.todo.list.task_GetAttachmentSession",
      "parameters": [
        {
          "name": "user-id",
          "in": "path",
          "description": "The unique identifier of user",
          "required": true,
          "style": "simple",
          "schema": {
            "type": "string"
          },
          "x-ms-docs-key-type": "user"
        },
        {
          "name": "todoTaskList-id",
          "in": "path",
          "description": "The unique identifier of todoTaskList",
          "required": true,
          "style": "simple",
          "schema": {
            "type": "string"
          },
          "x-ms-docs-key-type": "todoTaskList"
        },
        {
          "name": "todoTask-id",
          "in": "path",
          "description": "The unique identifier of todoTask",
          "required": true,
          "style": "simple",
          "schema": {
            "type": "string"
          },
          "x-ms-docs-key-type": "todoTask"
        },
        {
          "name": "attachmentSession-id",
          "in": "path",
          "description": "The unique identifier of attachmentSession",
          "required": true,
          "style": "simple",
          "schema": {
            "type": "string"
          },
          "x-ms-docs-key-type": "attachmentSession"
        },
        {
          "name": "$select",
          "in": "query",
          "description": "Select properties to be returned",
          "style": "form",
          "explode": false,
          "schema": {
            "uniqueItems": true,
            "type": "array",
            "items": {
              "type": "string"
            }
          }
        },
        {
          "name": "$expand",
          "in": "query",
          "description": "Expand related entities",
          "style": "form",
          "explode": false,
          "schema": {
            "uniqueItems": true,
            "type": "array",
            "items": {
              "type": "string"
            }
          }
        }
      ],
      "responses": {
        "2XX": {
          "description": "Retrieved navigation property",
          "content": {
            "application/json": {
              "schema": {
                "$ref": "#/components/schemas/microsoft.graph.attachmentSession"
              }
            }
          }
        },
        "default": {
          "$ref": "#/components/responses/error"
        }
      },
      "deprecated": true,
      "x-ms-deprecation": {
        "removalDate": "2025-07-02",
        "date": "2024-07-02",
        "version": "2024-07/PrivatePreview:copilotExportAPI"
      },
      "x-ms-docs-operation-type": "operation"
    },
    "patch": {
      "tags": [
        "users.todo"
      ],
      "summary": "Update the navigation property attachmentSessions in users",
      "operationId": "user.todo.list.task_UpdateAttachmentSession",
      "parameters": [
        {
          "name": "user-id",
          "in": "path",
          "description": "The unique identifier of user",
          "required": true,
          "style": "simple",
          "schema": {
            "type": "string"
          },
          "x-ms-docs-key-type": "user"
        },
        {
          "name": "todoTaskList-id",
          "in": "path",
          "description": "The unique identifier of todoTaskList",
          "required": true,
          "style": "simple",
          "schema": {
            "type": "string"
          },
          "x-ms-docs-key-type": "todoTaskList"
        },
        {
          "name": "todoTask-id",
          "in": "path",
          "description": "The unique identifier of todoTask",
          "required": true,
          "style": "simple",
          "schema": {
            "type": "string"
          },
          "x-ms-docs-key-type": "todoTask"
        },
        {
          "name": "attachmentSession-id",
          "in": "path",
          "description": "The unique identifier of attachmentSession",
          "required": true,
          "style": "simple",
          "schema": {
            "type": "string"
          },
          "x-ms-docs-key-type": "attachmentSession"
        }
      ],
      "requestBody": {
        "description": "New navigation property values",
        "content": {
          "application/json": {
            "schema": {
              "$ref": "#/components/schemas/microsoft.graph.attachmentSession"
            }
          }
        },
        "required": true
      },
      "responses": {
        "2XX": {
          "description": "Success",
          "content": {
            "application/json": {
              "schema": {
                "$ref": "#/components/schemas/microsoft.graph.attachmentSession"
              }
            }
          }
        },
        "default": {
          "$ref": "#/components/responses/error"
        }
      },
      "deprecated": true,
      "x-ms-deprecation": {
        "removalDate": "2025-07-02",
        "date": "2024-07-02",
        "version": "2024-07/PrivatePreview:copilotExportAPI"
      },
      "x-ms-docs-operation-type": "operation"
    },
    "delete": {
      "tags": [
        "users.todo"
      ],
      "summary": "Delete navigation property attachmentSessions for users",
      "operationId": "user.todo.list.task_DeleteAttachmentSession",
      "parameters": [
        {
          "name": "user-id",
          "in": "path",
          "description": "The unique identifier of user",
          "required": true,
          "style": "simple",
          "schema": {
            "type": "string"
          },
          "x-ms-docs-key-type": "user"
        },
        {
          "name": "todoTaskList-id",
          "in": "path",
          "description": "The unique identifier of todoTaskList",
          "required": true,
          "style": "simple",
          "schema": {
            "type": "string"
          },
          "x-ms-docs-key-type": "todoTaskList"
        },
        {
          "name": "todoTask-id",
          "in": "path",
          "description": "The unique identifier of todoTask",
          "required": true,
          "style": "simple",
          "schema": {
            "type": "string"
          },
          "x-ms-docs-key-type": "todoTask"
        },
        {
          "name": "attachmentSession-id",
          "in": "path",
          "description": "The unique identifier of attachmentSession",
          "required": true,
          "style": "simple",
          "schema": {
            "type": "string"
          },
          "x-ms-docs-key-type": "attachmentSession"
        },
        {
          "name": "If-Match",
          "in": "header",
          "description": "ETag",
          "style": "simple",
          "schema": {
            "type": "string"
          }
        }
      ],
      "responses": {
        "2XX": {
          "description": "Success"
        },
        "default": {
          "$ref": "#/components/responses/error"
        }
      },
      "deprecated": true,
      "x-ms-deprecation": {
        "removalDate": "2025-07-02",
        "date": "2024-07-02",
        "version": "2024-07/PrivatePreview:copilotExportAPI"
      },
      "x-ms-docs-operation-type": "operation"
    }
  }
}